warthog/__init__.py
warthog/app_config.py
warthog/cache.py
warthog/conf.py
warthog/context.py
warthog/data_structures.py
warthog/default_settings.py
warthog/loaders.py
warthog/managers.py
warthog/middleware.py
warthog/models.py
warthog/render.py
warthog/urls.py
warthog/views.py
warthog/admin/__init__.py
warthog/admin/forms.py
warthog/migrations/0001_initial.py
warthog/migrations/__init__.py
warthog/migrations_south/0001_initial.py
warthog/migrations_south/0002_add_child_types_collection.py
warthog/migrations_south/0003_auto_generate_path_start.py
warthog/migrations_south/0004_migrate_path_data.py
warthog/migrations_south/0005_auto_generate_path_finish.py
warthog/migrations_south/0006_add_edit_lock.py
warthog/migrations_south/0007_add_sites_to_templates.py
warthog/migrations_south/0008_add_sites.py
warthog/migrations_south/0009_correct_unique_constraint.py
warthog/migrations_south/0010_remove_uri_path_unique_constraint.py
warthog/migrations_south/__init__.py
warthog/resource_types/__init__.py
warthog/resource_types/fields.py
warthog/resource_types/uploads.py
warthog/static/admin/css/warthog.css
warthog/static/admin/css/img/warthog-sprite.png
warthog/templates/admin/warthog/change_list.html
warthog/templates/warthog/html5.html
warthog/templatetags/__init__.py
warthog/templatetags/cms_include.py
warthog/templatetags/cms_tags.py
warthog/tests/__init__.py
warthog/tests/cache.py
warthog/tests/models.py
django_warthog-0.5.2.0.dist-info/LICENSE
django_warthog-0.5.2.0.dist-info/METADATA
django_warthog-0.5.2.0.dist-info/WHEEL
django_warthog-0.5.2.0.dist-info/top_level.txt
django_warthog-0.5.2.0.dist-info/RECORD
