Metadata-Version: 2.1
Name: django-warthog
Version: 0.5.2.0
Summary: Embeddable CMS for Django.
Home-page: https://www.github.com/timsavage/django-warthog
Author: Tim Savage
Author-email: tim@savage.company
License: BSD License
Platform: OS Independent
Classifier: Development Status :: 5 - Production/Stable
Classifier: Environment :: Web Environment
Classifier: Framework :: Django
Classifier: Intended Audience :: Developers
Classifier: Operating System :: OS Independent
Classifier: Programming Language :: Python
Classifier: Topic :: Internet :: WWW/HTTP :: Dynamic Content
Classifier: Topic :: Software Development
Classifier: Topic :: Software Development :: Libraries :: Application Frameworks
Requires-Dist: Django (>=1.4)
